watson_machine_learning_client/__init__.py
watson_machine_learning_client/client.py
watson_machine_learning_client/definitions.py
watson_machine_learning_client/deployments.py
watson_machine_learning_client/experiments.py
watson_machine_learning_client/functions.py
watson_machine_learning_client/hpo.py
watson_machine_learning_client/href_definitions.py
watson_machine_learning_client/instance.py
watson_machine_learning_client/learning_system.py
watson_machine_learning_client/log_util.py
watson_machine_learning_client/metanames.py
watson_machine_learning_client/models.py
watson_machine_learning_client/repository.py
watson_machine_learning_client/runtimes.py
watson_machine_learning_client/training.py
watson_machine_learning_client/utils.py
watson_machine_learning_client/wml_client_error.py
watson_machine_learning_client/wml_resource.py
watson_machine_learning_client/libs/__init__.py
watson_machine_learning_client/libs/mlpipelinepy/__init__.py
watson_machine_learning_client/libs/mlpipelinepy/edge.py
watson_machine_learning_client/libs/mlpipelinepy/exception.py
watson_machine_learning_client/libs/mlpipelinepy/javaproxy.py
watson_machine_learning_client/libs/mlpipelinepy/mlpipeline.py
watson_machine_learning_client/libs/mlpipelinepy/serialization.py
watson_machine_learning_client/libs/mlpipelinepy/utils.py
watson_machine_learning_client/libs/mlpipelinepy/version.py
watson_machine_learning_client/libs/pipeline/DAG.py
watson_machine_learning_client/libs/pipeline/IBMSparkPipeline.py
watson_machine_learning_client/libs/pipeline/IBMSparkPipelineModel.py
watson_machine_learning_client/libs/pipeline/Result.py
watson_machine_learning_client/libs/pipeline/Sink.py
watson_machine_learning_client/libs/pipeline/Source.py
watson_machine_learning_client/libs/pipeline/Wrapper.py
watson_machine_learning_client/libs/pipeline/__init__.py
watson_machine_learning_client/libs/repo/TestRepoSaveLoad.py
watson_machine_learning_client/libs/repo/__init__.py
watson_machine_learning_client-1.0.391.dist-info/LICENSE.txt
watson_machine_learning_client-1.0.391.dist-info/METADATA
watson_machine_learning_client-1.0.391.dist-info/WHEEL
watson_machine_learning_client-1.0.391.dist-info/top_level.txt
watson_machine_learning_client-1.0.391.dist-info/RECORD
