Metadata-Version: 2.1
Name: watson-machine-learning-client
Version: 1.0.391
Summary: Watson Machine Learning API Client
Home-page: http://wml-api-pyclient.mybluemix.net
Author: IBM
Author-email: lukasz.cmielowski@pl.ibm.com, maria.oleszkiewicz@pl.ibm.com, wojciech.sobala@pl.ibm.com
License: BSD
Keywords: watson,machine learning,IBM,Bluemix,client,API,IBM Cloud
Platform: UNKNOWN
Classifier: Development Status :: 5 - Production/Stable
Classifier: Natural Language :: English
Classifier: License :: OSI Approved :: BSD License
Classifier: Programming Language :: Python :: 2.7
Classifier: Programming Language :: Python :: 3.5
Classifier: Programming Language :: Python :: 3.6
Classifier: Operating System :: MacOS :: MacOS X
Classifier: Operating System :: Microsoft :: Windows
Classifier: Operating System :: POSIX :: Linux
Classifier: Intended Audience :: Science/Research
Classifier: Intended Audience :: Developers
Classifier: Intended Audience :: Information Technology
Classifier: Topic :: Software Development :: Libraries
Classifier: Topic :: Software Development :: Libraries :: Python Modules
Classifier: Topic :: Scientific/Engineering :: Artificial Intelligence
Classifier: Topic :: Scientific/Engineering :: Information Analysis
Classifier: Topic :: Internet
Requires-Dist: requests
Requires-Dist: urllib3
Requires-Dist: pandas
Requires-Dist: certifi
Requires-Dist: tqdm
Requires-Dist: lomond
Requires-Dist: tabulate
Requires-Dist: ibm-cos-sdk
Requires-Dist: boto3
